pymediator/__init__.py
pymediator/exceptions.py
pymediator/handlers.py
pymediator/mediator.py
pymediator/registry.py
pymediator/utils.py
pymediator-0.3.0.dist-info/LICENSE
pymediator-0.3.0.dist-info/METADATA
pymediator-0.3.0.dist-info/WHEEL
pymediator-0.3.0.dist-info/RECORD
