Metadata-Version: 2.1
Name: pymediator
Version: 0.3.0
Summary: Lightweight and extensible implementation of the Mediator pattern in Python
Home-page: https://github.com/serivt/pymediator
License: MIT
Author: Sergio Torrado
Requires-Python: >=3.10,<4.0
Classifier: License :: OSI Approved :: MIT License
Classifier: Programming Language :: Python :: 3
Classifier: Programming Language :: Python :: 3.10
Classifier: Programming Language :: Python :: 3.11
Classifier: Programming Language :: Python :: 3.12
Classifier: Programming Language :: Python :: 3.13
Project-URL: Repository, https://github.com/serivt/pymediator
